pyfsftpserver/__init__.py
pyfsftpserver/__main__.py
pyfsftpserver/server.py
pyfsftpserver/base/__init__.py
pyfsftpserver/base/default_context.py
pyfsftpserver/base/messages.py
pyfsftpserver/base/server.py
pyfsftpserver/base/shell.py
pyfsftpserver/base/utils.py
pyfsftpserver/base/prorocols/__init__.py
pyfsftpserver/base/prorocols/command_channel.py
pyfsftpserver/base/prorocols/data_channel.py
pyfsftpserver/base/prorocols/mlsx_format.py
pyfsftpserver/base/prorocols/protocol_interpreter.py
pyfsftpserver/di/__init__.py
pyfsftpserver/di/context.py
pyfsftpserver/patches/__init__.py
pyfsftpserver/patches/patched_gcsfs.py
pyfsftpserver/with_pyfs/__init__.py
pyfsftpserver/with_pyfs/aioexecutor.py
pyfsftpserver/with_pyfs/server.py
pyfsftpserver/with_pyfs/shell.py
pyfsftpserver-0.2.0.dist-info/LICENSE
pyfsftpserver-0.2.0.dist-info/METADATA
pyfsftpserver-0.2.0.dist-info/WHEEL
pyfsftpserver-0.2.0.dist-info/top_level.txt
pyfsftpserver-0.2.0.dist-info/RECORD
