Metadata-Version: 2.1
Name: pyfsftpserver
Version: 0.2.0
Summary: A simple ftp server for serving PyFilesystem2 filesystems.
Home-page: https://github.com/sorgloomer/pyfsftpserver
Author: Tamás László Hegedűs
Author-email: tamas.laszlo.hegedus@gmail.com
License: MIT
Download-URL: https://github.com/sorgloomer/pyfsftpserver/archive/v0.0.1.tar.gz
Keywords: ftp,server,asyncio,pyfs,pyfilesystem
Platform: UNKNOWN
Classifier: Development Status :: 3 - Alpha
Classifier: Intended Audience :: Developers
Classifier: Environment :: Console
Classifier: Topic :: System :: Filesystems
Classifier: License :: OSI Approved :: MIT License
Classifier: Operating System :: OS Independent
Classifier: Programming Language :: Python :: 3.6
Classifier: Programming Language :: Python :: 3.7
Classifier: Programming Language :: Python :: 3.8
Requires-Python: >=3.6
Requires-Dist: fs
